soft_assert/__init__.py
soft_assert/soft_assert.py
soft_assert-1.0.5.dist-info/LICENSE
soft_assert-1.0.5.dist-info/METADATA
soft_assert-1.0.5.dist-info/WHEEL
soft_assert-1.0.5.dist-info/top_level.txt
soft_assert-1.0.5.dist-info/RECORD
