Metadata-Version: 2.1
Name: soft-assert
Version: 1.0.5
Summary: Soft assertions for Python/Pytest
Home-page: https://github.com/pashkatrick/soft-assert
Author: pashkatrick
License-File: LICENSE
